microagg1d/__init__.py
microagg1d/algorithms_educational.py
microagg1d/algorithms_linear.py
microagg1d/algorithms_old.py
microagg1d/algorithms_other.py
microagg1d/common.py
microagg1d/cost_maxdist.py
microagg1d/cost_round.py
microagg1d/cost_sae.py
microagg1d/cost_sse.py
microagg1d/generation.py
microagg1d/main.py
microagg1d/multivariate_poly.py
microagg1d/smawk_iter2.py
microagg1d/smawk_old.py
microagg1d/user_facing.py
microagg1d/utils_for_test.py
microagg1d-0.4.0.dist-info/LICENSE
microagg1d-0.4.0.dist-info/METADATA
microagg1d-0.4.0.dist-info/WHEEL
microagg1d-0.4.0.dist-info/top_level.txt
microagg1d-0.4.0.dist-info/RECORD
