Metadata-Version: 2.1
Name: microagg1d
Version: 0.4.0
Summary: A package to perform optimal univariate microaggregation for various cost functions.
Author-email: "Felix I. Stamm" <felix.stamm@rwth-aachen.de>
License: BSD 2-Clause License
Project-URL: Homepage, https://github.com/Feelx234/microagg1d
Project-URL: Bug Tracker, https://github.com/Feelx234/microagg1d/issues
Keywords: microaggregation,clustering,kmeans,k-means,anonymity
Classifier: Programming Language :: Python :: 3
Classifier: License :: OSI Approved :: BSD License
Classifier: Operating System :: OS Independent
Requires-Python: >=3.9
License-File: LICENSE
Requires-Dist: numpy>=1.23.5
Requires-Dist: numba>=0.56.4
Provides-Extra: test
Requires-Dist: pytest; extra == "test"
Requires-Dist: pytest-cov; extra == "test"
Requires-Dist: coverage[toml]; extra == "test"
